unithandler/__init__.py
unithandler/base.py
unithandler/constants.py
unithandler/conversion.py
unithandler/siunits.py
unithandler-1.6.0.dist-info/LICENSE
unithandler-1.6.0.dist-info/METADATA
unithandler-1.6.0.dist-info/WHEEL
unithandler-1.6.0.dist-info/top_level.txt
unithandler-1.6.0.dist-info/RECORD
