Metadata-Version: 2.1
Name: unithandler
Version: 1.6.0
Summary: numeric mimic classes with units
Home-page: https://gitlab.com/larsyunker/unithandler
Author: Lars Yunker
License: MIT License
Project-URL: Documentation, https://unithandler.readthedocs.io/en/latest/index.html
Keywords: units,unit,float,int
Platform: UNKNOWN
Classifier: Programming Language :: Python :: 3
Classifier: License :: OSI Approved :: MIT License
Classifier: Development Status :: 5 - Production/Stable
Classifier: Intended Audience :: Science/Research
Classifier: Topic :: Scientific/Engineering :: Chemistry
Classifier: Topic :: Scientific/Engineering :: Information Analysis
Classifier: Operating System :: OS Independent
Classifier: Natural Language :: English
Requires-Python: >=3
License-File: LICENSE
